request_pressure_tracker/__init__.py
request_pressure_tracker/notifiers/__init__.py
request_pressure_tracker/notifiers/azure_monitoring.py
request_pressure_tracker/notifiers/base.py
request_pressure_tracker/notifiers/cloudwatch.py
request_pressure_tracker/notifiers/django_cache.py
request_pressure_tracker/trackers/__init__.py
request_pressure_tracker/trackers/base.py
request_pressure_tracker/trackers/memory.py
request_pressure_tracker/wsgi_django/__init__.py
request_pressure_tracker/wsgi_django/azure.py
request_pressure_tracker/wsgi_django/base.py
request_pressure_tracker/wsgi_django/cache.py
request_pressure_tracker/wsgi_django/cloudwatch.py
request_time_tracker/__init__.py
request_time_tracker/django_wsgi.py
request_time_tracker/wsgi.py
request_time_tracker/notifiers/__init__.py
request_time_tracker/notifiers/azure_monitoring.py
request_time_tracker/notifiers/base.py
request_time_tracker/notifiers/cloudwatch.py
request_time_tracker/notifiers/django_cache.py
request_time_tracker/trackers/__init__.py
request_time_tracker/trackers/base.py
request_time_tracker/trackers/memory.py
request_time_tracker/trackers/cache/__init__.py
request_time_tracker/trackers/cache/base.py
request_time_tracker/trackers/cache/django.py
request_time_tracker/trackers/cache/redis.py
request_time_tracker/wsgi_django/__init__.py
request_time_tracker/wsgi_django/azure.py
request_time_tracker/wsgi_django/base.py
request_time_tracker/wsgi_django/cache.py
request_time_tracker/wsgi_django/cloudwatch.py
request_time_tracker/wsgi_django/legacy.py
request_time_tracker-0.0.20.dist-info/METADATA
request_time_tracker-0.0.20.dist-info/WHEEL
request_time_tracker-0.0.20.dist-info/top_level.txt
request_time_tracker-0.0.20.dist-info/RECORD
