Metadata-Version: 2.1
Name: request-time-tracker
Version: 0.0.20
Summary: Requests time tracker from being captured by proxy (e.g. nginx) till being executed by wsgi handler
Home-page: https://github.com/razortheory/request-time-tracker
Author: Roman Karpovich
Author-email: roman@razortheory.com
Project-URL: Home, https://github.com/razortheory/request-time-tracker
Project-URL: Bug Tracker, https://github.com/razortheory/request-time-tracker/issues
Classifier: Programming Language :: Python :: 3
Classifier: License :: OSI Approved :: MIT License
Classifier: Operating System :: OS Independent
Requires-Python: >=3.6
Provides-Extra: aws
Requires-Dist: boto3 ; extra == 'aws'
Provides-Extra: azure
Requires-Dist: requests ; extra == 'azure'
Provides-Extra: redis
Requires-Dist: redis ; extra == 'redis'
